{
  "__type__": "cc.SpriteFrame",
  "content": {
    "name": "zhiwu_4",
    "atlas": "",
    "rect": {
      "x": 0,
      "y": 0,
      "width": 210,
      "height": 319
    },
    "offset": {
      "x": 0,
      "y": 0
    },
    "originalSize": {
      "width": 210,
      "height": 319
    },
    "rotated": false,
    "capInsets": [
      0,
      0,
      0,
      0
    ],
    "vertices": {
      "rawPosition": [
        -105,
        -159.5,
        0,
        105,
        -159.5,
        0,
        -105,
        159.5,
        0,
        105,
        159.5,
        0
      ],
      "indexes": [
        0,
        1,
        2,
        2,
        1,
        3
      ],
      "uv": [
        0,
        319,
        210,
        319,
        0,
        0,
        210,
        0
      ],
      "nuv": [
        0,
        0,
        1,
        0,
        0,
        1,
        1,
        1
      ],
      "minPos": {
        "x": -105,
        "y": -159.5,
        "z": 0
      },
      "maxPos": {
        "x": 105,
        "y": 159.5,
        "z": 0
      }
    },
    "texture": "bc1f8201-5074-41aa-8986-f4dd4bf5c678@6c48a",
    "packable": true,
    "pixelsToUnit": 100,
    "pivot": {
      "x": 0.5,
      "y": 0.5
    },
    "meshType": 0
  }
}